nitterguest/__init__.py
nitterguest/cli.py
nitterguest/const.py
nitterguest/nitter_guest.py
nitterguest/token_file_organizer.py
nitterguest/version.py
nitterguest-0.1.2.dist-info/METADATA
nitterguest-0.1.2.dist-info/WHEEL
nitterguest-0.1.2.dist-info/entry_points.txt
nitterguest-0.1.2.dist-info/RECORD
