Metadata-Version: 2.1
Name: nitterguest
Version: 0.1.2
Summary: 
Home-page: https://github.com/386jp/nitterguest
Author: Kyosuke Miyamura
Author-email: ask@386.jp
Requires-Python: >=3.9
Classifier: Programming Language :: Python :: 3
Classifier: Programming Language :: Python :: 3.9
Classifier: Programming Language :: Python :: 3.10
Classifier: Programming Language :: Python :: 3.11
Requires-Dist: requests (>=2.31.0,<3.0.0)
Requires-Dist: schedule (>=1.2.1,<2.0.0)
Project-URL: Repository, https://github.com/386jp/nitterguest
